sp00kyvectors/__init__.py
sp00kyvectors/cnn.py
sp00kyvectors/core.py
sp00kyvectors/dataframes.py
sp00kyvectors/load_images.py
sp00kyvectors/neural_net.py
sp00kyvectors/notbooks/dataframe_ex.ipynb
sp00kyvectors/notbooks/dev.ipynb
sp00kyvectors/notbooks/sandbox.ipynb
sp00kyvectors/utils.py
sp00kyvectors-0.1.15.dist-info/LICENSE
sp00kyvectors-0.1.15.dist-info/METADATA
sp00kyvectors-0.1.15.dist-info/WHEEL
sp00kyvectors-0.1.15.dist-info/RECORD
