Metadata-Version: 2.3
Name: Sp00kyVectors
Version: 0.1.15
Summary: A spooky vector analysis library
License: MIT
Author: Lila James
Author-email: lilaresearch@gmail.com
Requires-Python: >=3.10,<4.0
Classifier: License :: OSI Approved :: MIT License
Classifier: Programming Language :: Python :: 3
Classifier: Programming Language :: Python :: 3.10
Classifier: Programming Language :: Python :: 3.11
Classifier: Programming Language :: Python :: 3.12
Classifier: Programming Language :: Python :: 3.13
Requires-Dist: appnope (==0.1.4)
Requires-Dist: asttokens (==3.0.0)
Requires-Dist: certifi (==2025.4.26)
Requires-Dist: charset-normalizer (==3.4.2)
Requires-Dist: comm (==0.2.2)
Requires-Dist: contourpy (==1.3.2)
Requires-Dist: cycler (==0.12.1)
Requires-Dist: debugpy (==1.8.14)
Requires-Dist: decorator (==5.2.1)
Requires-Dist: docutils (==0.21.2)
Requires-Dist: executing (==2.2.0)
Requires-Dist: fonttools (==4.58.0)
Requires-Dist: id (==1.5.0)
Requires-Dist: idna (==3.10)
Requires-Dist: iniconfig (==2.1.0)
Requires-Dist: ipykernel (==6.29.5)
Requires-Dist: ipython (==9.2.0)
Requires-Dist: ipython-pygments-lexers (==1.1.1)
Requires-Dist: jaraco-classes (==3.4.0)
Requires-Dist: jaraco-context (==6.0.1)
Requires-Dist: jaraco-functools (==4.1.0)
Requires-Dist: jedi (==0.19.2)
Requires-Dist: joblib (==1.5.0)
Requires-Dist: jupyter-client (==8.6.3)
Requires-Dist: jupyter-core (==5.7.2)
Requires-Dist: keyring (==25.6.0)
Requires-Dist: kiwisolver (==1.4.8)
Requires-Dist: markdown-it-py (==3.0.0)
Requires-Dist: matplotlib (==3.10.1)
Requires-Dist: matplotlib-inline (==0.1.7)
Requires-Dist: mdurl (==0.1.2)
Requires-Dist: more-itertools (==10.7.0)
Requires-Dist: nest-asyncio (==1.6.0)
Requires-Dist: nh3 (==0.2.21)
Requires-Dist: numpy (==1.26.4)
Requires-Dist: opencv-python (>=4.9.0.80,<5.0.0.0)
Requires-Dist: packaging (==25.0)
Requires-Dist: pandas (==2.2.3)
Requires-Dist: parso (==0.8.4)
Requires-Dist: pexpect (==4.9.0)
Requires-Dist: pillow (==11.2.1)
Requires-Dist: platformdirs (==4.3.8)
Requires-Dist: pluggy (==1.6.0)
Requires-Dist: prompt-toolkit (==3.0.51)
Requires-Dist: psutil (==7.0.0)
Requires-Dist: ptyprocess (==0.7.0)
Requires-Dist: pure-eval (==0.2.3)
Requires-Dist: pygments (==2.19.1)
Requires-Dist: pyparsing (==3.2.3)
Requires-Dist: pytest (==8.3.5)
Requires-Dist: python-dateutil (==2.9.0.post0)
Requires-Dist: pytz (==2025.2)
Requires-Dist: pyzmq (==26.4.0)
Requires-Dist: readme-renderer (==44.0)
Requires-Dist: requests (==2.32.3)
Requires-Dist: requests-toolbelt (==1.0.0)
Requires-Dist: rfc3986 (==2.0.0)
Requires-Dist: rich (==14.0.0)
Requires-Dist: scikit-learn (==1.6.1)
Requires-Dist: scipy (==1.15.2)
Requires-Dist: six (==1.17.0)
Requires-Dist: stack-data (==0.6.3)
Requires-Dist: threadpoolctl (==3.6.0)
Requires-Dist: torch (>=2.3.0,<3.0.0)
Requires-Dist: tornado (==6.5)
Requires-Dist: tqdm (==4.67.1)
Requires-Dist: traitlets (==5.14.3)
Requires-Dist: twine (==6.1.0)
Requires-Dist: tzdata (==2025.2)
Requires-Dist: urllib3 (==2.4.0)
Requires-Dist: wcwidth (==0.2.13)
